<?xml version="1.0" encoding="UTF-8"?>
<?xml-stylesheet type="text/xsl" href="Crane-gc2html.xsl"?>
<?Crane-gc2ods indentation Save with indentation?>
<?Crane-gc2ods encoding UTF-8?>
<gc:CodeList xmlns:gc="http://docs.oasis-open.org/codelist/ns/genericode/1.0/">
   <Annotation>
      <Description>KIK-Inzage specifieke waardelijst, ter vervanging van enumeraties in de xsd</Description>
   </Annotation>
   <Identification>
      <ShortName>Registercode</ShortName>
      <LongName>Registercode</LongName>
      <Version>2013-06-13</Version>
      <CanonicalUri>Registercode</CanonicalUri>
      <CanonicalVersionUri>Registercode20130613</CanonicalVersionUri>
      <LocationUri>https://service1.kadaster.nl/kik/waardelijsten/i_Registercode.xml</LocationUri>
   </Identification>
   <ColumnSet>
      <Column Id="Code" Use="required">
         <ShortName>Code</ShortName>
         <Data Type="String"/>
      </Column>
      <Column Id="Waarde" Use="required">
         <ShortName>Waarde</ShortName>
         <Data Type="String"/>
      </Column>
      <Column Id="DatumVanaf" Use="optional">
         <ShortName>DatumVanaf</ShortName>
         <Data Type="date"/>
      </Column>
      <Column Id="DatumTot" Use="optional">
         <ShortName>DatumTot</ShortName>
         <Data Type="date"/>
      </Column>
      <Key Id="CodeKey">
         <ShortName>key for column 'Code'</ShortName>
         <ColumnRef Ref="Code"/>
      </Key>
      <Key Id="WaardeKey">
         <ShortName>key for column 'Waarde'</ShortName>
         <ColumnRef Ref="Waarde"/>
      </Key>
   </ColumnSet>
   <SimpleCodeList>
      <Row>
         <Value ColumnRef="Code">
            <SimpleValue>1</SimpleValue>
         </Value>
         <Value ColumnRef="Waarde">
            <SimpleValue>2Bl</SimpleValue>
         </Value>
      </Row>
      <Row>
         <Value ColumnRef="Code">
            <SimpleValue>2</SimpleValue>
         </Value>
         <Value ColumnRef="Waarde">
            <SimpleValue>4</SimpleValue>
         </Value>
      </Row>
      <Row>
         <Value ColumnRef="Code">
            <SimpleValue>3</SimpleValue>
         </Value>
         <Value ColumnRef="Waarde">
            <SimpleValue>4D</SimpleValue>
         </Value>
      </Row>
      <Row>
         <Value ColumnRef="Code">
            <SimpleValue>4</SimpleValue>
         </Value>
         <Value ColumnRef="Waarde">
            <SimpleValue>51</SimpleValue>
         </Value>
      </Row>
      <Row>
         <Value ColumnRef="Code">
            <SimpleValue>5</SimpleValue>
         </Value>
         <Value ColumnRef="Waarde">
            <SimpleValue>75</SimpleValue>
         </Value>
      </Row>
      <Row>
         <Value ColumnRef="Code">
            <SimpleValue>6</SimpleValue>
         </Value>
         <Value ColumnRef="Waarde">
            <SimpleValue>75A</SimpleValue>
         </Value>
      </Row>
      <Row>
         <Value ColumnRef="Code">
            <SimpleValue>7</SimpleValue>
         </Value>
         <Value ColumnRef="Waarde">
            <SimpleValue>75B</SimpleValue>
         </Value>
      </Row>
      <Row>
         <Value ColumnRef="Code">
            <SimpleValue>8</SimpleValue>
         </Value>
         <Value ColumnRef="Waarde">
            <SimpleValue>84</SimpleValue>
         </Value>
      </Row>
      <Row>
         <Value ColumnRef="Code">
            <SimpleValue>9</SimpleValue>
         </Value>
         <Value ColumnRef="Waarde">
            <SimpleValue>110</SimpleValue>
         </Value>
      </Row>
      <Row>
         <Value ColumnRef="Code">
            <SimpleValue>10</SimpleValue>
         </Value>
         <Value ColumnRef="Waarde">
            <SimpleValue>ACG</SimpleValue>
         </Value>
      </Row>
      <Row>
         <Value ColumnRef="Code">
            <SimpleValue>11</SimpleValue>
         </Value>
         <Value ColumnRef="Waarde">
            <SimpleValue>ACS</SimpleValue>
         </Value>
      </Row>
      <Row>
         <Value ColumnRef="Code">
            <SimpleValue>12</SimpleValue>
         </Value>
         <Value ColumnRef="Waarde">
            <SimpleValue>ADR</SimpleValue>
         </Value>
      </Row>
      <Row>
         <Value ColumnRef="Code">
            <SimpleValue>13</SimpleValue>
         </Value>
         <Value ColumnRef="Waarde">
            <SimpleValue>AHV</SimpleValue>
         </Value>
      </Row>
      <Row>
         <Value ColumnRef="Code">
            <SimpleValue>14</SimpleValue>
         </Value>
         <Value ColumnRef="Waarde">
            <SimpleValue>ATG</SimpleValue>
         </Value>
      </Row>
      <Row>
         <Value ColumnRef="Code">
            <SimpleValue>15</SimpleValue>
         </Value>
         <Value ColumnRef="Waarde">
            <SimpleValue>AVH</SimpleValue>
         </Value>
      </Row>
      <Row>
         <Value ColumnRef="Code">
            <SimpleValue>16</SimpleValue>
         </Value>
         <Value ColumnRef="Waarde">
            <SimpleValue>AVK</SimpleValue>
         </Value>
      </Row>
      <Row>
         <Value ColumnRef="Code">
            <SimpleValue>17</SimpleValue>
         </Value>
         <Value ColumnRef="Waarde">
            <SimpleValue>AWZ</SimpleValue>
         </Value>
      </Row>
      <Row>
         <Value ColumnRef="Code">
            <SimpleValue>18</SimpleValue>
         </Value>
         <Value ColumnRef="Waarde">
            <SimpleValue>BCF</SimpleValue>
         </Value>
      </Row>
      <Row>
         <Value ColumnRef="Code">
            <SimpleValue>19</SimpleValue>
         </Value>
         <Value ColumnRef="Waarde">
            <SimpleValue>BLK</SimpleValue>
         </Value>
      </Row>
      <Row>
         <Value ColumnRef="Code">
            <SimpleValue>20</SimpleValue>
         </Value>
         <Value ColumnRef="Waarde">
            <SimpleValue>BSA</SimpleValue>
         </Value>
      </Row>
      <Row>
         <Value ColumnRef="Code">
            <SimpleValue>21</SimpleValue>
         </Value>
         <Value ColumnRef="Waarde">
            <SimpleValue>BTO</SimpleValue>
         </Value>
      </Row>
      <Row>
         <Value ColumnRef="Code">
            <SimpleValue>22</SimpleValue>
         </Value>
         <Value ColumnRef="Waarde">
            <SimpleValue>BVG</SimpleValue>
         </Value>
      </Row>
      <Row>
         <Value ColumnRef="Code">
            <SimpleValue>23</SimpleValue>
         </Value>
         <Value ColumnRef="Waarde">
            <SimpleValue>CDB</SimpleValue>
         </Value>
      </Row>
      <Row>
         <Value ColumnRef="Code">
            <SimpleValue>24</SimpleValue>
         </Value>
         <Value ColumnRef="Waarde">
            <SimpleValue>DB</SimpleValue>
         </Value>
      </Row>
      <Row>
         <Value ColumnRef="Code">
            <SimpleValue>25</SimpleValue>
         </Value>
         <Value ColumnRef="Waarde">
            <SimpleValue>DBB</SimpleValue>
         </Value>
      </Row>
      <Row>
         <Value ColumnRef="Code">
            <SimpleValue>26</SimpleValue>
         </Value>
         <Value ColumnRef="Waarde">
            <SimpleValue>DO</SimpleValue>
         </Value>
      </Row>
      <Row>
         <Value ColumnRef="Code">
            <SimpleValue>27</SimpleValue>
         </Value>
         <Value ColumnRef="Waarde">
            <SimpleValue>GBO</SimpleValue>
         </Value>
      </Row>
      <Row>
         <Value ColumnRef="Code">
            <SimpleValue>28</SimpleValue>
         </Value>
         <Value ColumnRef="Waarde">
            <SimpleValue>HNW</SimpleValue>
         </Value>
      </Row>
      <Row>
         <Value ColumnRef="Code">
            <SimpleValue>29</SimpleValue>
         </Value>
         <Value ColumnRef="Waarde">
            <SimpleValue>IBB</SimpleValue>
         </Value>
      </Row>
      <Row>
         <Value ColumnRef="Code">
            <SimpleValue>30</SimpleValue>
         </Value>
         <Value ColumnRef="Waarde">
            <SimpleValue>INQ</SimpleValue>
         </Value>
      </Row>
      <Row>
         <Value ColumnRef="Code">
            <SimpleValue>31</SimpleValue>
         </Value>
         <Value ColumnRef="Waarde">
            <SimpleValue>KON</SimpleValue>
         </Value>
      </Row>
      <Row>
         <Value ColumnRef="Code">
            <SimpleValue>32</SimpleValue>
         </Value>
         <Value ColumnRef="Waarde">
            <SimpleValue>KPA</SimpleValue>
         </Value>
      </Row>
      <Row>
         <Value ColumnRef="Code">
            <SimpleValue>33</SimpleValue>
         </Value>
         <Value ColumnRef="Waarde">
            <SimpleValue>LBD</SimpleValue>
         </Value>
      </Row>
      <Row>
         <Value ColumnRef="Code">
            <SimpleValue>34</SimpleValue>
         </Value>
         <Value ColumnRef="Waarde">
            <SimpleValue>LWB</SimpleValue>
         </Value>
      </Row>
      <Row>
         <Value ColumnRef="Code">
            <SimpleValue>35</SimpleValue>
         </Value>
         <Value ColumnRef="Waarde">
            <SimpleValue>MAG</SimpleValue>
         </Value>
      </Row>
      <Row>
         <Value ColumnRef="Code">
            <SimpleValue>36</SimpleValue>
         </Value>
         <Value ColumnRef="Waarde">
            <SimpleValue>MBW</SimpleValue>
         </Value>
      </Row>
      <Row>
         <Value ColumnRef="Code">
            <SimpleValue>37</SimpleValue>
         </Value>
         <Value ColumnRef="Waarde">
            <SimpleValue>MIL</SimpleValue>
         </Value>
      </Row>
      <Row>
         <Value ColumnRef="Code">
            <SimpleValue>38</SimpleValue>
         </Value>
         <Value ColumnRef="Waarde">
            <SimpleValue>MVA</SimpleValue>
         </Value>
      </Row>
      <Row>
         <Value ColumnRef="Code">
            <SimpleValue>39</SimpleValue>
         </Value>
         <Value ColumnRef="Waarde">
            <SimpleValue>MVK</SimpleValue>
         </Value>
      </Row>
      <Row>
         <Value ColumnRef="Code">
            <SimpleValue>40</SimpleValue>
         </Value>
         <Value ColumnRef="Waarde">
            <SimpleValue>NNW</SimpleValue>
         </Value>
      </Row>
      <Row>
         <Value ColumnRef="Code">
            <SimpleValue>41</SimpleValue>
         </Value>
         <Value ColumnRef="Waarde">
            <SimpleValue>ODB</SimpleValue>
         </Value>
      </Row>
      <Row>
         <Value ColumnRef="Code">
            <SimpleValue>42</SimpleValue>
         </Value>
         <Value ColumnRef="Waarde">
            <SimpleValue>OSR</SimpleValue>
         </Value>
      </Row>
      <Row>
         <Value ColumnRef="Code">
            <SimpleValue>43</SimpleValue>
         </Value>
         <Value ColumnRef="Waarde">
            <SimpleValue>OVO</SimpleValue>
         </Value>
      </Row>
      <Row>
         <Value ColumnRef="Code">
            <SimpleValue>44</SimpleValue>
         </Value>
         <Value ColumnRef="Waarde">
            <SimpleValue>POS</SimpleValue>
         </Value>
      </Row>
      <Row>
         <Value ColumnRef="Code">
            <SimpleValue>45</SimpleValue>
         </Value>
         <Value ColumnRef="Waarde">
            <SimpleValue>PTT</SimpleValue>
         </Value>
      </Row>
      <Row>
         <Value ColumnRef="Code">
            <SimpleValue>46</SimpleValue>
         </Value>
         <Value ColumnRef="Waarde">
            <SimpleValue>REC</SimpleValue>
         </Value>
      </Row>
      <Row>
         <Value ColumnRef="Code">
            <SimpleValue>47</SimpleValue>
         </Value>
         <Value ColumnRef="Waarde">
            <SimpleValue>R14</SimpleValue>
         </Value>
      </Row>
      <Row>
         <Value ColumnRef="Code">
            <SimpleValue>48</SimpleValue>
         </Value>
         <Value ColumnRef="Waarde">
            <SimpleValue>SBB</SimpleValue>
         </Value>
      </Row>
      <Row>
         <Value ColumnRef="Code">
            <SimpleValue>49</SimpleValue>
         </Value>
         <Value ColumnRef="Waarde">
            <SimpleValue>SYN</SimpleValue>
         </Value>
      </Row>
      <Row>
         <Value ColumnRef="Code">
            <SimpleValue>50</SimpleValue>
         </Value>
         <Value ColumnRef="Waarde">
            <SimpleValue>TAE</SimpleValue>
         </Value>
      </Row>
      <Row>
         <Value ColumnRef="Code">
            <SimpleValue>51</SimpleValue>
         </Value>
         <Value ColumnRef="Waarde">
            <SimpleValue>TPV</SimpleValue>
         </Value>
      </Row>
      <Row>
         <Value ColumnRef="Code">
            <SimpleValue>52</SimpleValue>
         </Value>
         <Value ColumnRef="Waarde">
            <SimpleValue>UVO</SimpleValue>
         </Value>
      </Row>
      <Row>
         <Value ColumnRef="Code">
            <SimpleValue>53</SimpleValue>
         </Value>
         <Value ColumnRef="Waarde">
            <SimpleValue>VKV</SimpleValue>
         </Value>
      </Row>
      <Row>
         <Value ColumnRef="Code">
            <SimpleValue>54</SimpleValue>
         </Value>
         <Value ColumnRef="Waarde">
            <SimpleValue>VNB</SimpleValue>
         </Value>
      </Row>
      <Row>
         <Value ColumnRef="Code">
            <SimpleValue>55</SimpleValue>
         </Value>
         <Value ColumnRef="Waarde">
            <SimpleValue>VOS</SimpleValue>
         </Value>
      </Row>
      <Row>
         <Value ColumnRef="Code">
            <SimpleValue>56</SimpleValue>
         </Value>
         <Value ColumnRef="Waarde">
            <SimpleValue>WPB</SimpleValue>
         </Value>
      </Row>
      <Row>
         <Value ColumnRef="Code">
            <SimpleValue>57</SimpleValue>
         </Value>
         <Value ColumnRef="Waarde">
            <SimpleValue>WPT</SimpleValue>
         </Value>
      </Row>
      <Row>
         <Value ColumnRef="Code">
            <SimpleValue>58</SimpleValue>
         </Value>
         <Value ColumnRef="Waarde">
            <SimpleValue>WZN</SimpleValue>
         </Value>
      </Row>
      <Row>
         <Value ColumnRef="Code">
            <SimpleValue>59</SimpleValue>
         </Value>
         <Value ColumnRef="Waarde">
            <SimpleValue>3</SimpleValue>
         </Value>
      </Row>
   </SimpleCodeList>
</gc:CodeList>